LICENSE
README.rst
setup.cfg
setup.py
src/pdf2redmine/__init__.py
src/pdf2redmine/main.py
src/pdf2redmine.egg-info/PKG-INFO
src/pdf2redmine.egg-info/SOURCES.txt
src/pdf2redmine.egg-info/dependency_links.txt
src/pdf2redmine.egg-info/top_level.txt