Metadata-Version: 2.1
Name: pdf2redmine
Version: 1.1
Summary: A software tool to automatically read a pdf docuument for annotations (comments) and upload those to a redmine server using a personal API access token
Home-page: https://github.com/TobiasGlaubach/pdf2redmine
Author: Tobias Glaubach
License: UNKNOWN
Project-URL: Bug Tracker, https://github.com/TobiasGlaubach/pdf2redmine/issues
Platform: UNKNOWN
Classifier: License :: OSI Approved :: GNU General Public License v3 or later (GPLv3+)
Classifier: Operating System :: OS Independent
Classifier: Environment :: Console
Classifier: Programming Language :: Python
Classifier: Programming Language :: Python :: 3
Classifier: Programming Language :: Python :: 3 :: Only
Requires-Python: >=3.8
License-File: LICENSE
